md_to_conf/__init__.py
md_to_conf/client.py
md_to_conf/confluence_converter.py
md_to_conf/converter.py
md_to_conf-1.1.2.dist-info/licenses/LICENSE
md_to_conf-1.1.2.dist-info/METADATA
md_to_conf-1.1.2.dist-info/WHEEL
md_to_conf-1.1.2.dist-info/entry_points.txt
md_to_conf-1.1.2.dist-info/top_level.txt
md_to_conf-1.1.2.dist-info/RECORD
