Metadata-Version: 2.4
Name: md-to-conf
Version: 1.1.2
Summary: Markdown to Confluence Cloud Publisher
Home-page: https://github.com/spydersoft-consulting/md_to_conf
Author: Matt Gerega
Classifier: Programming Language :: Python :: 3 :: Only
License-File: LICENSE
Requires-Dist: certifi
Requires-Dist: chardet
Requires-Dist: idna
Requires-Dist: Markdown
Requires-Dist: requests
Requires-Dist: mdx_truly_sane_lists
Dynamic: author
Dynamic: classifier
Dynamic: description
Dynamic: description-content-type
Dynamic: home-page
Dynamic: license-file
Dynamic: requires-dist
Dynamic: summary
